baseflow/__init__.py
baseflow/comparision.py
baseflow/example.csv
baseflow/param_estimate.py
baseflow/separation.py
baseflow/thawed.npz
baseflow/utils.py
baseflow/methods/Boughton.py
baseflow/methods/CM.py
baseflow/methods/Chapman.py
baseflow/methods/EWMA.py
baseflow/methods/Eckhardt.py
baseflow/methods/Fixed.py
baseflow/methods/Furey.py
baseflow/methods/LH.py
baseflow/methods/Local.py
baseflow/methods/Slide.py
baseflow/methods/UKIH.py
baseflow/methods/Willems.py
baseflow/methods/__init__.py
baseflow-0.1.0.dist-info/METADATA
baseflow-0.1.0.dist-info/WHEEL
baseflow-0.1.0.dist-info/top_level.txt
baseflow-0.1.0.dist-info/RECORD
