Metadata-Version: 2.2
Name: baseflow
Version: 0.1.0
Summary: A python package for baseflow separation
Home-page: https://github.com/xiejx5/baseflow
Author: Cody James
Author-email: xiejx5@gmail.com
License: MIT
Classifier: License :: OSI Approved :: MIT License
Classifier: Programming Language :: Python
Classifier: Programming Language :: Python :: 3
Classifier: Programming Language :: Python :: 3.6
Classifier: Programming Language :: Python :: Implementation :: CPython
Classifier: Programming Language :: Python :: Implementation :: PyPy
Requires-Python: >=3.6.0
Requires-Dist: numpy
Requires-Dist: numba
Requires-Dist: tqdm
Requires-Dist: pandas
Provides-Extra: fancy-feature
Requires-Dist: matplotlib; extra == "fancy-feature"
Requires-Dist: scipy; extra == "fancy-feature"
Dynamic: author
Dynamic: author-email
Dynamic: classifier
Dynamic: description
Dynamic: description-content-type
Dynamic: home-page
Dynamic: license
Dynamic: provides-extra
Dynamic: requires-dist
Dynamic: requires-python
Dynamic: summary
